muuntuu/__init__.py
muuntuu/__main__.py
muuntuu/api.py
muuntuu/cli.py
muuntuu/implementation.py
muuntuu-2025.12.5.dist-info/licenses/LICENSE
muuntuu-2025.12.5.dist-info/METADATA
muuntuu-2025.12.5.dist-info/WHEEL
muuntuu-2025.12.5.dist-info/entry_points.txt
muuntuu-2025.12.5.dist-info/top_level.txt
muuntuu-2025.12.5.dist-info/RECORD
