Metadata-Version: 2.4
Name: muuntuu
Version: 2025.12.5
Summary: Transforms (Finnish: muuntuu) helper tool.
Author-email: Stefan Hagen <stefan@hagen.link>
Maintainer-email: Stefan Hagen <stefan@hagen.link>
License-Expression: MIT
Project-URL: Documentation, https://codes.dilettant.life/docs/muuntuu
Project-URL: Test-Coverage, https://codes.dilettant.life/coverage/muuntuu
Keywords: author-tools,developer-tools,JSON,YAML
Classifier: Development Status :: 3 - Alpha
Classifier: Intended Audience :: Developers
Classifier: Programming Language :: Python :: 3.10
Classifier: Programming Language :: Python :: 3.11
Classifier: Programming Language :: Python :: 3.12
Classifier: Programming Language :: Python :: 3.13
Classifier: Programming Language :: Python :: 3.14
Classifier: Programming Language :: Python :: 3.9
Requires-Python: >=3.9
License-File: LICENSE
Requires-Dist: ruamel.yaml>=0.18.16
Dynamic: license-file
